ai_pose_generator_4/__init__.py
ai_pose_generator_4-1767000.119.247.dist-info/licenses/LICENSE
ai_pose_generator_4-1767000.119.247.dist-info/METADATA
ai_pose_generator_4-1767000.119.247.dist-info/WHEEL
ai_pose_generator_4-1767000.119.247.dist-info/top_level.txt
ai_pose_generator_4-1767000.119.247.dist-info/RECORD
